[
    {
        "id": "RES-1",
        "instalacion": "Tennis 1",
        "habitacion": "101",
        "fecha": "2026-03-02",
        "hora_inicio": "10:00",
        "hora_fin": "11:00",
        "personas": 2,
        "nombre": "Juan Pérez",
        "autor": "Admin",
        "comentarios": "Raquetas",
        "created_at": "2026-03-02T02:48:08.000Z",
        "hotel_id": 1
    },
    {
        "id": "RES-10",
        "instalacion": "Ping Pong",
        "habitacion": "505",
        "fecha": "2026-03-02",
        "hora_inicio": "11:30",
        "hora_fin": "12:00",
        "personas": 2,
        "nombre": "Niños 505",
        "autor": "Admin",
        "comentarios": "",
        "created_at": "2026-03-02T02:48:08.000Z",
        "hotel_id": 1
    },
    {
        "id": "RES-101",
        "instalacion": "SPA",
        "habitacion": "101",
        "fecha": "2026-03-02",
        "hora_inicio": "10:00",
        "hora_fin": "11:00",
        "personas": 2,
        "nombre": "John Doe",
        "autor": "Admin",
        "comentarios": "Reserva de circuito termal",
        "created_at": "2026-03-02T03:00:54.000Z",
        "hotel_id": 1
    },
    {
        "id": "RES-102",
        "instalacion": "Tennis 1",
        "habitacion": "202",
        "fecha": "2026-03-02",
        "hora_inicio": "11:00",
        "hora_fin": "12:00",
        "personas": 4,
        "nombre": "Grupo Amigos",
        "autor": "Recepcion1",
        "comentarios": "",
        "created_at": "2026-03-02T03:00:54.000Z",
        "hotel_id": 1
    },
    {
        "id": "RES-103",
        "instalacion": "Padel 1",
        "habitacion": "305",
        "fecha": "2026-03-02",
        "hora_inicio": "12:00",
        "hora_fin": "13:00",
        "personas": 2,
        "nombre": "John Doe",
        "autor": "Admin",
        "comentarios": "",
        "created_at": "2026-03-02T03:00:54.000Z",
        "hotel_id": 1
    },
    {
        "id": "RES-104",
        "instalacion": "Spa Privado",
        "habitacion": "410",
        "fecha": "2026-03-02",
        "hora_inicio": "17:00",
        "hora_fin": "18:00",
        "personas": 2,
        "nombre": "Pareja VIP",
        "autor": "Recepcion1",
        "comentarios": "Cava",
        "created_at": "2026-03-02T03:00:54.000Z",
        "hotel_id": 1
    },
    {
        "id": "RES-105",
        "instalacion": "Gimnasio PT",
        "habitacion": "501",
        "fecha": "2026-03-02",
        "hora_inicio": "08:00",
        "hora_fin": "09:00",
        "personas": 1,
        "nombre": "Entrenamiento",
        "autor": "Admin",
        "comentarios": "Coach",
        "created_at": "2026-03-02T03:00:54.000Z",
        "hotel_id": 1
    },
    {
        "id": "RES-2",
        "instalacion": "Padel 1",
        "habitacion": "202",
        "fecha": "2026-03-02",
        "hora_inicio": "11:00",
        "hora_fin": "12:00",
        "personas": 4,
        "nombre": "Grupo Amigos",
        "autor": "Recepcion1",
        "comentarios": "",
        "created_at": "2026-03-02T02:48:08.000Z",
        "hotel_id": 1
    },
    {
        "id": "RES-3",
        "instalacion": "Tennis 1",
        "habitacion": "305",
        "fecha": "2026-03-02",
        "hora_inicio": "12:00",
        "hora_fin": "13:00",
        "personas": 2,
        "nombre": "John Doe",
        "autor": "Admin",
        "comentarios": "",
        "created_at": "2026-03-02T02:48:08.000Z",
        "hotel_id": 1
    },
    {
        "id": "RES-4",
        "instalacion": "Spa Privado",
        "habitacion": "410",
        "fecha": "2026-03-02",
        "hora_inicio": "17:00",
        "hora_fin": "18:00",
        "personas": 2,
        "nombre": "Pareja VIP",
        "autor": "Recepcion1",
        "comentarios": "Cava",
        "created_at": "2026-03-02T02:48:08.000Z",
        "hotel_id": 1
    },
    {
        "id": "RES-5",
        "instalacion": "Gimnasio PT",
        "habitacion": "501",
        "fecha": "2026-03-02",
        "hora_inicio": "08:00",
        "hora_fin": "09:00",
        "personas": 1,
        "nombre": "Entrenamiento",
        "autor": "Admin",
        "comentarios": "Coach",
        "created_at": "2026-03-02T02:48:08.000Z",
        "hotel_id": 1
    },
    {
        "id": "RES-6",
        "instalacion": "Tennis 2",
        "habitacion": "105",
        "fecha": "2026-03-02",
        "hora_inicio": "09:00",
        "hora_fin": "10:00",
        "personas": 2,
        "nombre": "Player 1",
        "autor": "Admin",
        "comentarios": "Bolas",
        "created_at": "2026-03-02T02:48:08.000Z",
        "hotel_id": 1
    },
    {
        "id": "RES-7",
        "instalacion": "Padel 2",
        "habitacion": "212",
        "fecha": "2026-03-02",
        "hora_inicio": "19:00",
        "hora_fin": "20:30",
        "personas": 4,
        "nombre": "Huésped 212",
        "autor": "Recepcion2",
        "comentarios": "Luz",
        "created_at": "2026-03-02T02:48:08.000Z",
        "hotel_id": 1
    },
    {
        "id": "RES-8",
        "instalacion": "Sala Reuniones",
        "habitacion": "314",
        "fecha": "2026-03-02",
        "hora_inicio": "15:00",
        "hora_fin": "17:00",
        "personas": 10,
        "nombre": "Empresa X",
        "autor": "Admin",
        "comentarios": "Proyector",
        "created_at": "2026-03-02T02:48:08.000Z",
        "hotel_id": 1
    },
    {
        "id": "RES-9",
        "instalacion": "Bicicletas",
        "habitacion": "402",
        "fecha": "2026-03-02",
        "hora_inicio": "10:00",
        "hora_fin": "14:00",
        "personas": 2,
        "nombre": "Ciclistas",
        "autor": "Recepcion1",
        "comentarios": "Cascos",
        "created_at": "2026-03-02T02:48:08.000Z",
        "hotel_id": 1
    },
    {
        "id": "RES-1773278715180",
        "instalacion": "Cancha de tennis",
        "habitacion": "104",
        "fecha": "2026-03-12",
        "hora_inicio": "12:20",
        "hora_fin": "13:20",
        "pax": 1,
        "nombre_cliente": "",
        "observaciones": "",
        "externo": false,
        "timestamp": 1773278715180,
        "autor": "Anadelia",
        "actualizadoEn": "2026-03-12T01:25:15.180Z"
    }
]